Metadata-Version: 2.1
Name: slapr
Version: 1.3
Summary: A simple tool that allows you to change your default AWS CLI profile.
Home-page: https://github.com/antonipy/slapr
Author: Antoni Yanev
Author-email: antonipyanev@gmail.com
License: gpl-3.0
Download-URL: https://github.com/antonipy/slapr/archive/refs/tags/1.3.tar.gz
Keywords: aws,awscli,awscliv2,linux,tools
Platform: UNKNOWN
Classifier: Development Status :: 5 - Production/Stable
Classifier: Intended Audience :: Developers
Classifier: Intended Audience :: Developers
Classifier: Intended Audience :: System Administrators
Classifier: Topic :: Internet
Classifier: Topic :: Software Development :: Build Tools
Classifier: Topic :: Utilities
Classifier: License :: OSI Approved :: GNU General Public License v3 (GPLv3)
Classifier: Programming Language :: Python :: 3.6
Classifier: Programming Language :: Python :: 3.7
Classifier: Programming Language :: Python :: 3.8
Classifier: Programming Language :: Python :: 3.9
License-File: LICENSE.txt
